LICENSE.txt
README.md
setup.cfg
setup.py
bea_data/__init__.py
bea_data/bea_data.py
bea_data.egg-info/PKG-INFO
bea_data.egg-info/SOURCES.txt
bea_data.egg-info/dependency_links.txt
bea_data.egg-info/requires.txt
bea_data.egg-info/top_level.txt