Metadata-Version: 1.1
Name: bea-data
Version: 1.0
Summary: A python library that interacts with the Burea of Econmic Analysis API
Home-page: https://github.com/a-finocchiaro/bea_project
Author: Aaron Finocchiaro
Author-email: afinny10@gmail.com
License: MIT
Download-URL: https://github.com/a-finocchiaro/bea_project/archive/v_1.tar.gz
Keywords: Pandas,Economic,Analysis,Bureau
Platform: UNKNOWN
Classifier: Development Status :: 3 - Alpha
Classifier: Intended Audience :: Developers
Classifier: Topic :: Software Development :: Build Tools
Classifier: License :: OSI Approved :: MIT License
Classifier: Programming Language :: Python :: 3.7
Classifier: Programming Language :: Python :: 3.8
Classifier: Programming Language :: Python :: 3.9
